odoo/addons/sale_coupon_multi_use/README.rst
odoo/addons/sale_coupon_multi_use/__init__.py
odoo/addons/sale_coupon_multi_use/__manifest__.py
odoo/addons/sale_coupon_multi_use/i18n/fr.po
odoo/addons/sale_coupon_multi_use/i18n/sale_coupon_multi_use.pot
odoo/addons/sale_coupon_multi_use/models/__init__.py
odoo/addons/sale_coupon_multi_use/models/sale_coupon.py
odoo/addons/sale_coupon_multi_use/models/sale_coupon_consumption_line.py
odoo/addons/sale_coupon_multi_use/models/sale_coupon_program.py
odoo/addons/sale_coupon_multi_use/models/sale_order.py
odoo/addons/sale_coupon_multi_use/models/sale_order_line.py
odoo/addons/sale_coupon_multi_use/readme/CONTRIBUTORS.rst
odoo/addons/sale_coupon_multi_use/readme/DESCRIPTION.rst
odoo/addons/sale_coupon_multi_use/security/ir.model.access.csv
odoo/addons/sale_coupon_multi_use/static/description/icon.png
odoo/addons/sale_coupon_multi_use/static/description/index.html
odoo/addons/sale_coupon_multi_use/tests/__init__.py
odoo/addons/sale_coupon_multi_use/tests/common.py
odoo/addons/sale_coupon_multi_use/tests/test_sale_coupon_use.py
odoo/addons/sale_coupon_multi_use/views/sale_coupon_program_views.xml
odoo/addons/sale_coupon_multi_use/views/sale_coupon_views.xml
odoo/addons/sale_coupon_multi_use/wizards/__init__.py
odoo/addons/sale_coupon_multi_use/wizards/sale_coupon_apply_code.py
odoo13_addon_sale_coupon_multi_use-13.0.1.0.2.dist-info/METADATA
odoo13_addon_sale_coupon_multi_use-13.0.1.0.2.dist-info/WHEEL
odoo13_addon_sale_coupon_multi_use-13.0.1.0.2.dist-info/top_level.txt
odoo13_addon_sale_coupon_multi_use-13.0.1.0.2.dist-info/RECORD
